peerrtc/__init__.py
peerrtc-0.0.1.dist-info/METADATA
peerrtc-0.0.1.dist-info/WHEEL
peerrtc-0.0.1.dist-info/top_level.txt
peerrtc-0.0.1.dist-info/RECORD
