Metadata-Version: 2.1
Name: peerrtc
Version: 0.0.1
Summary: peerrtc
Home-page: https://github.com/CoLearn-Dev/fleece-network
Requires-Python: >=3.10
